LICENSE
MANIFEST.in
package.json
requirements.txt
setup.py
material/404.html
material/__init__.py
material/base.html
material/main.html
material/assets/images/favicon-old.png
material/assets/images/favicon.ico
material/assets/images/favicon.png
material/assets/images/logo_white.png
material/assets/images/icons/bitbucket-670608a71a.svg
material/assets/images/icons/github-1da075986e.svg
material/assets/images/icons/gitlab-5ad3f9f9e5.svg
material/assets/javascripts/application-68832431b5.js
material/assets/javascripts/headroom.min.js
material/assets/javascripts/jQuery.headroom.min.js
material/assets/javascripts/jq-mdc-web.js
material/assets/javascripts/modernizr-e826f8942a.js
material/assets/javascripts/lunr/lunr.da.js
material/assets/javascripts/lunr/lunr.de.js
material/assets/javascripts/lunr/lunr.du.js
material/assets/javascripts/lunr/lunr.es.js
material/assets/javascripts/lunr/lunr.fi.js
material/assets/javascripts/lunr/lunr.fr.js
material/assets/javascripts/lunr/lunr.hu.js
material/assets/javascripts/lunr/lunr.it.js
material/assets/javascripts/lunr/lunr.jp.js
material/assets/javascripts/lunr/lunr.multi.js
material/assets/javascripts/lunr/lunr.no.js
material/assets/javascripts/lunr/lunr.pt.js
material/assets/javascripts/lunr/lunr.ro.js
material/assets/javascripts/lunr/lunr.ru.js
material/assets/javascripts/lunr/lunr.stemmer.support.js
material/assets/javascripts/lunr/lunr.sv.js
material/assets/javascripts/lunr/lunr.tr.js
material/assets/javascripts/lunr/tinyseg.js
material/assets/stylesheets/application-035c261bc5.palette.css
material/assets/stylesheets/application-2cd7d9ab0f.css
material/assets/stylesheets/material-components-web.min.css
material/assets/stylesheets/mdc-web.css
material/partials/disqus.html
material/partials/footer.html
material/partials/header.html
material/partials/header9.html
material/partials/language.html
material/partials/nav-item.html
material/partials/nav.html
material/partials/password.html
material/partials/search.html
mkdocs_material_components.egg-info/PKG-INFO
mkdocs_material_components.egg-info/SOURCES.txt
mkdocs_material_components.egg-info/dependency_links.txt
mkdocs_material_components.egg-info/entry_points.txt
mkdocs_material_components.egg-info/not-zip-safe
mkdocs_material_components.egg-info/requires.txt
mkdocs_material_components.egg-info/top_level.txt
