Metadata-Version: 1.0
Name: mkdocs-material-components
Version: 1.10.12
Summary: A Material Components Web theme for MkDocs
Home-page: http://yakworks.github.io/mkdocs-material-components/
Author: Martin Donath, Joshua Burnett
Author-email: martin.donath@squidfunk.com, joshdev@9ci.com
License: MIT
Keywords: mkdocs,documentation,theme
Platform: UNKNOWN
